[
    {
        "created_at_utc": "2025-09-24 12:59:59.036329",
        "id": "01K5XWYB5QY02XT0ET9R1031SX",
        "is_primary": 1,
        "kind": "email",
        "person_id": "01K5XWYB5QY02XT0ET9R1031SV",
        "updated_at_utc": "2025-09-24 12:59:59.036338",
        "value": "joeybagodonuts@safenet.org"
    },
    {
        "created_at_utc": "2025-09-24 12:59:59.036342",
        "id": "01K5XWYB5QY02XT0ET9R1031SY",
        "is_primary": 0,
        "kind": "phone",
        "person_id": "01K5XWYB5QY02XT0ET9R1031SV",
        "updated_at_utc": "2025-09-24 12:59:59.036345",
        "value": "+18005551212"
    },
    {
        "created_at_utc": "2025-09-24 17:21:31.350611",
        "id": "01K5YBX7PN1630P3MYNM80T9F5",
        "is_primary": 1,
        "kind": "email",
        "person_id": "01K5YBX7P636C2KHV79MTPE5KH",
        "updated_at_utc": "2025-09-24 17:21:31.350617",
        "value": "signsimian@protonmail.com"
    },
    {
        "created_at_utc": "2025-09-24 17:21:31.351478",
        "id": "01K5YBX7PQZ8E21B9DFFXSECVW",
        "is_primary": 1,
        "kind": "phone",
        "person_id": "01K5YBX7P636C2KHV79MTPE5KH",
        "updated_at_utc": "2025-09-24 17:21:31.351483",
        "value": "+19289208654"
    },
    {
        "created_at_utc": "2025-09-24 18:02:28.463019",
        "id": "01K5YE877E7YW2KE011E4K7HTT",
        "is_primary": 1,
        "kind": "email",
        "person_id": "01K5YE8774Q2M3DBVT2S94HVGS",
        "updated_at_utc": "2025-09-24 18:02:28.463025",
        "value": "alice@thelookingglass.org"
    },
    {
        "created_at_utc": "2025-09-24 18:02:28.463785",
        "id": "01K5YE877F7Z1DTHR8YN3SEZE5",
        "is_primary": 1,
        "kind": "phone",
        "person_id": "01K5YE8774Q2M3DBVT2S94HVGS",
        "updated_at_utc": "2025-09-24 18:02:28.463790",
        "value": "+15055559876"
    }
]